dominator/__init__.py
dominator/app.py
dominator-0.0.0b0.post1.dist-info/LICENSE
dominator-0.0.0b0.post1.dist-info/METADATA
dominator-0.0.0b0.post1.dist-info/WHEEL
dominator-0.0.0b0.post1.dist-info/top_level.txt
dominator-0.0.0b0.post1.dist-info/RECORD
