Metadata-Version: 2.1
Name: dominator
Version: 0.0.0b0.post1
Summary: UNKNOWN
Home-page: https://github.com/FFY00/dominator
Author: Filipe Laíns
Author-email: lains@riseup.net
License: EUPL 1.2
Platform: UNKNOWN
Classifier: License :: OSI Approved :: European Union Public Licence 1.2 (EUPL 1.2)
Classifier: Programming Language :: Python :: 3.7
Classifier: Programming Language :: Python :: 3.8
Classifier: Programming Language :: Python :: 3.9
Requires-Python: <4,>=3.7
Requires-Dist: tornado
Provides-Extra: app
Requires-Dist: webruntime ; extra == 'app'
Provides-Extra: test
Requires-Dist: pytest ; extra == 'test'
Requires-Dist: pytest-cov ; extra == 'test'
